adaptive_cards_templating_py/__init__.py
adaptive_cards_templating_py/dot_dict.py
adaptive_cards_templating_py/prebuilt_functions.py
adaptive_cards_templating_py/template_engine.py
adaptive_cards_templating_py-0.1.5.dist-info/licenses/LICENSE
adaptive_cards_templating_py-0.1.5.dist-info/METADATA
adaptive_cards_templating_py-0.1.5.dist-info/WHEEL
adaptive_cards_templating_py-0.1.5.dist-info/top_level.txt
adaptive_cards_templating_py-0.1.5.dist-info/RECORD
