Metadata-Version: 2.4
Name: adaptive_cards_templating_py
Version: 0.1.5
Summary: This library largely implements the JSON-to-JSON Adaptive Cards Template language for Python. Most features are supported, except for the Adaptive expressions prebuilt functions.
Author-email: Dion Olsthoorn <dion.olsthoorn@gmail.com>
License: MIT License
Project-URL: Homepage, https://github.com/dionoid/adaptive-cards-templating-py
Project-URL: Source, https://github.com/dionoid/adaptive-cards-templating-py
Project-URL: Issues, https://github.com/dionoid/adaptive-cards-templating-py/issues
Requires-Python: >=3.7
License-File: LICENSE
Provides-Extra: test
Requires-Dist: pytest; extra == "test"
Dynamic: license-file
